<InvalidateCache name="InvalidateCache-No-Prefix-Specific-Entry">
  <Scope>Application</Scope>
  <CacheKey>
<!--
    <Prefix>myprefix</Prefix>
-->
    <KeyFragment ref='request.queryparam.id' />
  </CacheKey>
  <!--
    <CacheContext>
      <APIProxyName>application_that_added_the_entry</APIProxyName>
      <ProxyName>proxy_for_which_data_was_cached</ProxyName>
      <TargetName>endpoint_for_which_data_was_cached</TargetName>
    </CacheContext>
  -->
  <!--
      <PurgeChildEntries>true</PurgeChildEntries>
  -->
</InvalidateCache>
